fiftyone_db_ubuntu2204-0.4.0.data/purelib/fiftyone/db/__init__.py
fiftyone_db_ubuntu2204-0.4.0.data/purelib/fiftyone/db/bin/mongod
fiftyone_db_ubuntu2204-0.4.0.dist-info/LICENSE
fiftyone_db_ubuntu2204-0.4.0.dist-info/METADATA
fiftyone_db_ubuntu2204-0.4.0.dist-info/WHEEL
fiftyone_db_ubuntu2204-0.4.0.dist-info/top_level.txt
fiftyone_db_ubuntu2204-0.4.0.dist-info/RECORD
